{
    "我的世界钓鱼":["::50::你{mc_fish}","::50::你在丛林里{mc_fish_forest}"],
    "mc_fish":[
        "使用普通的钓杆钓到了{common_fish}",
        "使用海之眷顾I的钓杆钓到了{luck_of_the_sea_I}",
        "使用海之眷顾I的钓杆钓到了{luck_of_the_sea_II}",
        "使用海之眷顾I的钓杆钓到了{luck_of_the_sea_III}"
    ],
    "mc_fish_forest":[
        "使用普通的钓杆钓到了{common_fish_forest}",
        "使用海之眷顾I的钓杆钓到了{luck_of_the_sea_I_forest}",
        "使用海之眷顾II的钓杆钓到了{luck_of_the_sea_II_forest}",
        "使用海之眷顾III的钓杆钓到了{luck_of_the_sea_III_forest}"
    ],
    "common_fish":[
        "::17::{fish_fish}","{fish_treasure}","::2::{fish_rubbish}"
    ],
    "common_fish_forest":[
        "::17::{fish_fish}","{fish_treasure}","::2::{fish_rubbish_forest}"
    ],
    "luck_of_the_sea_I":[
        "::848::{fish_fish}","::71::{fish_treasure}","::81::{fish_rubbish}"
    ],
    "luck_of_the_sea_II":[
        "::847::{fish_fish}","::92::{fish_treasure}","::61::{fish_rubbish}"
    ],
    "luck_of_the_sea_III":[
        "::845::{fish_fish}","::113::{fish_treasure}","::42::{fish_rubbish}"
    ],
    "luck_of_the_sea_I_forest":[
        "::848::{fish_fish}","::71::{fish_treasure}","::81::{fish_rubbish_forest}"
    ],
    "luck_of_the_sea_II_forest":[
        "::847::{fish_fish}","::92::{fish_treasure}","::61::{fish_rubbish_forest}"
    ],
    "luck_of_the_sea_III_forest":[
        "::845::{fish_fish}","::113::{fish_treasure}","::42::{fish_rubbish_forest}"
    ],
    "fish_fish":[
        "::60::生鳕鱼","::25::生鲑鱼","::2::热带鱼","::13::河豚"
    ],
    "fish_treasure":[
        "弓","附魔书","钓鱼竿","命名牌","鹦鹉螺壳","鞍"
    ],
    "fish_rubbish":[
        "::10::碗","::2::钓鱼竿",
        "::10::皮革",
        "::10::皮革靴子",
        "::10::腐肉",
        "::5::木棍","::5::线",
        "::10::水瓶",
        "::10::骨头",
        "墨囊*10","::10::绊线钩",
        "::17::睡莲"
    ],
    "fish_rubbish_forest":[
        "::10::竹子",
        "::10::碗","::2::钓鱼竿",
        "::10::皮革",
        "::10::皮革靴子",
        "::10::腐肉",
        "::5::木棍","::5::线",
        "::10::水瓶",
        "::10::骨头",
        "墨囊*10","::10::绊线钩",
        "::17::睡莲"
    ],
    "enchant_armor":[
        "::10::保护",
        "::5::摔落保护","::5::火焰保护",
        "::4::弹射物保护","::2::水下速掘","::2::爆炸保护",
        "::2::水下呼吸","::2::深海探索者","::2::冰霜行者","荆棘","绑定诅咒","灵魂疾行",
        "::5::耐久","::2::经验修补","消失诅咒"
    ],
    "enchart_bow":[
        "::10::力量",
        "::2::火矢","::2::冲击","无限",
        "::5::耐久","::2::经验修补","消失诅咒"
    ],
    "enchart_fishpole":[
        "::2::海之眷顾","::2::钓饵",
        "::5::耐久","::2::经验修补","消失诅咒"
    ]
}